vht_py/__init__.py
vht_py/__main__.py
vht_py/config.py
vht_py/library.py
vht_py/media.py
vht_py/options.py
vht_py/prompts.py
vht_py/system.py
vht_py/utils.py
vht_py-0.0.1.dist-info/LICENSE
vht_py-0.0.1.dist-info/METADATA
vht_py-0.0.1.dist-info/WHEEL
vht_py-0.0.1.dist-info/entry_points.txt
vht_py-0.0.1.dist-info/top_level.txt
vht_py-0.0.1.dist-info/RECORD
